gmthrash/__init__.py
gmthrash/crossedMolecularBeamsExperiment.py
gmthrash-1.0.6.data/scripts/GMTHRASH.py
gmthrash-1.0.6.data/scripts/GMTHRASH_cli.py
gmthrash-1.0.6.dist-info/METADATA
gmthrash-1.0.6.dist-info/WHEEL
gmthrash-1.0.6.dist-info/top_level.txt
gmthrash-1.0.6.dist-info/RECORD
