Metadata-Version: 2.4
Name: gmthrash
Version: 1.0.6
Summary: Forward Convolution Calculations for Crossed Molecular Beams Experiments
Home-page: https://github.com/kaka-zuumi/GMTHRASH
Author: Kazuumi Fujioka
Author-email: kazuumi@hawaii.edu
License: MIT
Requires-Dist: pandas
Requires-Dist: numpy
Requires-Dist: scipy
Requires-Dist: matplotlib
Requires-Dist: customtkinter
Dynamic: author
Dynamic: author-email
Dynamic: home-page
Dynamic: license
Dynamic: requires-dist
Dynamic: summary
